<data inherit_id="stock.report_delivery_document" priority="50">
    <xpath expr="//table[@name='stock_move_line_table']/thead/tr/th[2]" position="after">
        <th class="text-start">
            <strong>HS-Code</strong>
        </th>
         <th class="text-start">
            <strong>Origin</strong>
        </th>
    </xpath>
    <xpath expr="//table[@name='stock_backorder_table']/thead/tr/th[2]" position="before">
        <th class="text-start">
            <strong>HS-Code</strong>
        </th>
        <th class="text-start">
            <strong>Origin</strong>
        </th>
    </xpath>   
</data>